Metadata-Version: 2.4
Name: iflow-mcp_linkedin-mcp
Version: 0.1.2
Summary: Add your description here
Author-email: Hritik Raj <hritikraj_03@outlook.com>
Project-URL: Homepage, https://github.com/Hritik003/linkedin-mcp
Requires-Python: >=3.12
Requires-Dist: fastmcp>=0.4.1
Requires-Dist: linkedin-api>=2.3.1
Requires-Dist: python-dotenv>=1.0.1
Requires-Dist: requests>=2.32.3
Requires-Dist: uvicorn>=0.34.0
